{
  "letters": [
    "n",
    "w",
    "t",
    "e",
    "a",
    "o",
    "d",
    "c"
  ],
  "stages": [
    {
      "stage": "nwte",
      "words": [
        "newt",
        "went"
      ]
    },
    {
      "stage": "nwtea",
      "words": [
        "newt",
        "neat",
        "went",
        "wean",
        "want",
        "wane",
        "anew"
      ]
    },
    {
      "stage": "nwteao",
      "words": [
        "newt",
        "neat",
        "note",
        "went",
        "wean",
        "want",
        "wane",
        "wont",
        "tone",
        "town",
        "anew",
        "atone",
        "aeon"
      ]
    },
    {
      "stage": "nwteaod",
      "words": [
        "newt",
        "neat",
        "note",
        "noted",
        "node",
        "went",
        "wean",
        "want",
        "wanted",
        "wane",
        "waned",
        "wand",
        "wade",
        "wont",
        "tend",
        "tone",
        "toned",
        "town",
        "towed",
        "toed",
        "toad",
        "endow",
        "anew",
        "awed",
        "atone",
        "atoned",
        "aeon",
        "owned",
        "owed",
        "dent",
        "dean",
        "dawn",
        "date",
        "done",
        "donate",
        "down",
        "dote"
      ]
    },
    {
      "stage": "nwteaodc",
      "words": [
        "newt",
        "neat",
        "note",
        "noted",
        "node",
        "went",
        "wean",
        "want",
        "wanted",
        "wane",
        "waned",
        "wand",
        "wade",
        "wont",
        "tend",
        "taco",
        "tone",
        "toned",
        "town",
        "towed",
        "toed",
        "toad",
        "enact",
        "endow",
        "anew",
        "awed",
        "atone",
        "atoned",
        "aeon",
        "acne",
        "acted",
        "aced",
        "once",
        "owned",
        "owed",
        "ocean",
        "dent",
        "dean",
        "deacon",
        "dance",
        "dawn",
        "date",
        "done",
        "donate",
        "down",
        "dote",
        "cent",
        "cant",
        "cane",
        "caned",
        "canoe",
        "canoed",
        "cawed",
        "cadet",
        "cone",
        "cowed",
        "coat",
        "coated",
        "code"
      ]
    }
  ]
}